{"mappings": [{"item": {"url": "en/advanced/back-tracking/ab-string/", "title": "Chu\u1ed7i AB"}, "tags": ["chu\u1ed7i AB", "quay lui"]}, {"item": {"url": "en/advanced/back-tracking/balanced-parentheses/", "title": "Chu\u1ed7i ngo\u1eb7c h\u1ee3p l\u1ec7"}, "tags": ["chu\u1ed7i ngo\u1eb7c h\u1ee3p l\u1ec7", "quay lui"]}, {"item": {"url": "en/advanced/back-tracking/ternary-string/", "title": "Chu\u1ed7i tam ph\u00e2n"}, "tags": ["chu\u1ed7i tam ph\u00e2n", "quay lui"]}, {"item": {"url": "en/advanced/bitwise/ceiling-power-of-two/", "title": "Lu\u1ef9 th\u1eeba c\u1ee7a 2 g\u1ea7n nh\u1ea5t"}, "tags": ["Lu\u1ef9 th\u1eeba c\u1ee7a 2", "OR", "Ph\u00e9p d\u1ecbch ph\u1ea3i", "bitwise"]}, {"item": {"url": "en/advanced/bitwise/find-unique/", "title": "Ph\u1ea7n t\u1eed duy nh\u1ea5t trong m\u1ea3ng"}, "tags": ["Ph\u1ea7n t\u1eed duy nh\u1ea5t", "XOR", "bitwise"]}, {"item": {"url": "en/advanced/dynamic-programming/candy-pack/", "title": "Chia k\u1eb9o"}, "tags": ["quy ho\u1ea1ch \u0111\u1ed9ng", "t\u1ed5ng c\u1ee7a t\u1eadp con"]}, {"item": {"url": "en/advanced/dynamic-programming/inflorescences-and-jars/", "title": "C\u1eafm hoa"}, "tags": ["l\u1ef1a ch\u1ecdn t\u1ed1i \u01b0u v\u1edbi r\u00e0ng bu\u1ed9c th\u1ee9 t\u1ef1", "quy ho\u1ea1ch \u0111\u1ed9ng"]}, {"item": {"url": "en/advanced/dynamic-programming/knapsack/", "title": "Ba l\u00f4"}, "tags": ["ba l\u00f4", "quy ho\u1ea1ch \u0111\u1ed9ng"]}, {"item": {"url": "en/advanced/dynamic-programming/lis/", "title": "D\u00e3y con t\u0103ng d\u1ea7n d\u00e0i nh\u1ea5t"}, "tags": ["d\u00e3y con t\u0103ng d\u1ea7n d\u00e0i nh\u1ea5t", "quy ho\u1ea1ch \u0111\u1ed9ng"]}, {"item": {"url": "en/advanced/dynamic-programming/rewardstudent/", "title": "Chia ph\u1ea7n th\u01b0\u1edfng"}, "tags": ["ph\u00e2n t\u00edch th\u00e0nh t\u1ed5ng c\u1ee7a c\u00e1c s\u1ed1 t\u1ef1 nhi\u00ean", "quy ho\u1ea1ch \u0111\u1ed9ng"]}, {"item": {"url": "en/advanced/graph/escape-from-the-forest/", "title": "Tho\u00e1t kh\u1ecfi khu r\u1eebng"}, "tags": ["DFS", "\u00c1nh x\u1ea1 to\u1ea1 \u0111\u1ed9 2D th\u00e0nh 1D"]}, {"item": {"url": "en/advanced/graph/robot-in-the-maze/", "title": "Robot trong m\u00ea cung"}, "tags": ["BFS"]}, {"item": {"url": "en/solve-to-surpass/hsg12-tinh/2024-2025-nghean/", "title": "2024 - 2025 Ngh\u1ec7 An"}, "tags": ["m\u1ea3ng \u0111\u00e1nh d\u1ea5u", "s\u00e0ng Eratosthenes"]}, {"item": {"url": "en/solve-to-surpass/hsg12-tinh/2024-2025-tayninh-buoi-1/", "title": "2024 - 2025 T\u00e2y Ninh (bu\u1ed5i 1)"}, "tags": ["c\u00e2y", "c\u1eeda s\u1ed5 tr\u01b0\u1ee3t", "h\u00e0ng \u0111\u1ee3i", "m\u1ea3ng c\u1ed9ng d\u1ed3n", "quy ho\u1ea1ch \u0111\u1ed9ng", "t\u1ed5ng l\u1edbn nh\u1ea5t c\u1ee7a m\u1ea3ng con c\u00f3 \u0111\u1ed9 d\u00e0i ch\u1eb5n", "t\u1ed5ng ti\u1ec1n t\u1ed1"]}, {"item": {"url": "en/solve-to-surpass/hsg12-tinh/2025-2026-lamdong/", "title": "2025 - 2026 L\u00e2m \u0110\u1ed3ng"}, "tags": ["bitmask", "chu k\u1ef3 c\u1ee7a ch\u1eef s\u1ed1 t\u1eadn c\u00f9ng", "l\u0169y th\u1eeba nh\u1ecb ph\u00e2n", "nh\u00e1nh c\u1eadn", "quy ho\u1ea1ch \u0111\u1ed9ng", "t\u1ed5 h\u1ee3p"]}, {"item": {"url": "en/solve-to-surpass/hsg9-tinh/2022-2023-thuathienhue/", "title": "2022 - 2023 Th\u1eeba Thi\u00ean Hu\u1ebf"}, "tags": ["b\u1ed9i chung nh\u1ecf nh\u1ea5t", "chu\u1ed7i \u0111\u1ed1i x\u1ee9ng d\u00e0i nh\u1ea5t", "ph\u00e1t sinh t\u1ed5 h\u1ee3p theo th\u1ee9 t\u1ef1 t\u1eeb \u0111i\u1ec3n", "s\u1eafp x\u1ebfp", "\u01b0\u1edbc chung l\u1edbn nh\u1ea5t"]}, {"item": {"url": "en/solve-to-surpass/hsg9-tinh/2023-2024-camau/", "title": "2023 - 2024 C\u00e0 Mau"}, "tags": ["chu\u1ed7i", "gi\u00e1 tr\u1ecb l\u1edbn nh\u1ea5t", "m\u1ea3ng t\u1ea7n s\u1ed1", "s\u00e0ng nguy\u00ean t\u1ed1 Eratosthenes", "t\u1ed5ng ti\u1ec1n t\u1ed1", "\u0111\u1ebfm k\u00fd t\u1ef1"]}, {"item": {"url": "en/solve-to-surpass/hsg9-tinh/2023-2024-cantho/", "title": "2023 - 2024 C\u1ea7n Th\u01a1"}, "tags": ["chu\u1ed7i", "c\u1eb7p \u01b0\u1edbc s\u1ed1 (i, j) c\u1ee7a m\u1ed9t s\u1ed1 nguy\u00ean k sao cho i, j kh\u00f4ng v\u01b0\u1ee3t qu\u00e1 n", "c\u1eeda s\u1ed5 tr\u01b0\u1ee3t", "s\u1eafp x\u1ebfp"]}, {"item": {"url": "en/solve-to-surpass/hsg9-tinh/2023-2024-haiduong/", "title": "2023 - 2024 H\u1ea3i D\u01b0\u01a1ng"}, "tags": ["chia h\u1ebft c\u1ee7a t\u1ed5ng d\u00e3y s\u1ed1", "di\u1ec7n t\u00edch tam gi\u00e1c", "s\u1ed1 nghi\u1ec7m c\u1ee7a ph\u01b0\u01a1ng tr\u00ecnh", "s\u1ed1 nguy\u00ean t\u1ed1", "t\u1ed5ng c\u00e1c ch\u1eef s\u1ed1"]}, {"item": {"url": "en/solve-to-surpass/hsg9-tinh/2023-2024-hatinh-ts10/", "title": "2023 - 2024 H\u00e0 T\u0129nh tuy\u1ec3n sinh 10"}, "tags": ["bi\u1ebfn \u0111\u1ed5i bi\u1ec3u th\u1ee9c", "kho\u1ea3ng c\u00e1ch nh\u1ecf nh\u1ea5t ph\u1ee7 3 \u0111i\u1ec3m", "s\u1ed1 nguy\u00ean t\u1ed1", "t\u1ed5ng b\u00ecnh ph\u01b0\u01a1ng c\u00e1c ch\u1eef s\u1ed1 l\u00e0 nguy\u00ean t\u1ed1", "\u0111\u1ed9 d\u00e0i d\u00e3y con li\u00ean ti\u1ebfp l\u1edbn nh\u1ea5t"]}, {"item": {"url": "en/solve-to-surpass/hsg9-tinh/2023-2024-khanhhoa/", "title": "2023 - 2024 Kh\u00e1nh Ho\u00e0"}, "tags": ["b\u1ed9i s\u1ed1", "chu\u1ed7i", "m\u1ea3ng c\u1ed9ng d\u1ed3n", "m\u1ea3ng t\u1ea7n s\u1ed1", "s\u00e0ng nguy\u00ean t\u1ed1 Eratosthenes", "s\u1eafp x\u1ebfp", "t\u1ed5ng ti\u1ec1n t\u1ed1", "t\u1eeb d\u00e0i nh\u1ea5t", "\u0111\u1ebfm s\u1ed1 b\u1ed9i trong m\u1ed9t \u0111o\u1ea1n"]}, {"item": {"url": "en/solve-to-surpass/hsg9-tinh/2023-2024-thanhhoa/", "title": "2023 - 2024 Thanh Ho\u00e1"}, "tags": ["chu\u1ed7i", "s\u1ed1 c\u1eb7p c\u00f3 t\u1ed5ng nh\u1ecf h\u01a1n ho\u1eb7c b\u1eb1ng s\u1ed1 cho tr\u01b0\u1edbc", "s\u1ed1 c\u1eb7p nghi\u1ec7m nguy\u00ean d\u01b0\u01a1ng (x,y) c\u1ee7a b\u1ea5t ph\u01b0\u01a1ng tr\u00ecnh x + y <= n", "s\u1ed1 \u0111\u1ed1i x\u1ee9ng", "t\u00edch c\u1ee7a c\u00e1c th\u1eeba s\u1ed1 nguy\u00ean t\u1ed1", "\u0111\u1ebfm s\u1ed1 c\u1eb7p", "\u0111\u1ebfm t\u1ea7n s\u1ed1", "\u01b0\u1edbc nguy\u00ean t\u1ed1"]}, {"item": {"url": "en/solve-to-surpass/olympic10-hcm/2014-2015/", "title": "2014 - 2015"}, "tags": ["BFS", "hai con tr\u1ecf", "quy ho\u1ea1ch \u0111\u1ed9ng", "tham lam", "v\u00f9ng li\u00ean th\u00f4ng", "\u0111\u01b0\u1eddng \u0111i ng\u1eafn nh\u1ea5t"]}, {"item": {"url": "en/solve-to-surpass/olympic10-hcm/2020-2021/", "title": "2020 - 2021"}, "tags": ["s\u1eafp x\u1ebfp", "tham lam", "t\u00edch c\u1ee7a c\u00e1c th\u1eeba s\u1ed1 nguy\u00ean t\u1ed1"]}, {"item": {"url": "en/solve-to-surpass/olympic10-hcm/2024-2025/", "title": "2024 - 2025"}, "tags": ["bi\u1ebfn \u0111\u1ed5i to\u00e1n h\u1ecdc", "t\u00ecm ki\u1ebfm nh\u1ecb ph\u00e2n", "t\u1ed5ng l\u0169y k\u1ebf"]}, {"item": {"url": "en/solve-to-surpass/olympic11-hcm/2014-2015/", "title": "2014 - 2015"}, "tags": ["chu\u1ed7i nh\u1ecb ph\u00e2n", "ki\u1ec3u set", "t\u00ednh gi\u00e1 tr\u1ecb t\u1ea1i v\u1ecb tr\u00ed k", "x\u1ebfp h\u1ea1ng"]}]}